MANIFEST.in
README.rst
setup.cfg
setup.py
first_plugin_ida/__init__.py
first_plugin_ida/first.py
first_plugin_ida.egg-info/PKG-INFO
first_plugin_ida.egg-info/SOURCES.txt
first_plugin_ida.egg-info/dependency_links.txt
first_plugin_ida.egg-info/entry_points.txt
first_plugin_ida.egg-info/requires.txt
first_plugin_ida.egg-info/top_level.txt