Metadata-Version: 1.1
Name: first-plugin-ida
Version: 0.1.1
Summary: FIRST Integration: IDA Pro
Home-page: https://github.com/vrtadmin/FIRST-plugin-ida
Author: Angel M. Villegas
Author-email: first_@googlegroups.com
License: GPLv2
Keywords: first 1st reverse engineering ida pro
Platform: UNKNOWN
Classifier: Development Status :: 4 - Beta
Classifier: Intended Audience :: Information Technology
Classifier: Topic :: Software Development :: User Interfaces
Classifier: License :: OSI Approved :: GNU General Public License v2 (GPLv2)
Classifier: Programming Language :: Python :: 2.7
